hola_graph-0.1.5.dist-info/RECORD
hola_graph-0.1.5.dist-info/WHEEL
hola_graph-0.1.5.dist-info/METADATA
hola_graph-0.1.5.dist-info/licenses/LICENSE
hola_graph/_core.pyi
hola_graph/_core.cpython-314-darwin.so
hola_graph/_core.cpp
hola_graph/__init__.py
hola_graph/api.py
hola_graph/utils.py
hola_graph/py.typed
