Metadata-Version: 2.4
Name: hola-graph
Version: 0.1.5
Summary: A pybind11 wrapper to adaptagrams HOLA: Human-like Orthogonal Layout Algorithm.
Keywords: graph,layout,hola,orthogonal,diagram,visualization
Author-Email: Shakeeb Alireza <me@example.org>
License-Expression: MIT
Classifier: Development Status :: 4 - Beta
Classifier: Intended Audience :: Developers
Classifier: Intended Audience :: Science/Research
Classifier: Operating System :: MacOS
Classifier: Operating System :: POSIX :: Linux
Classifier: Programming Language :: C++
Classifier: Programming Language :: Python :: 3
Classifier: Programming Language :: Python :: 3.9
Classifier: Programming Language :: Python :: 3.10
Classifier: Programming Language :: Python :: 3.11
Classifier: Programming Language :: Python :: 3.12
Classifier: Programming Language :: Python :: 3.13
Classifier: Topic :: Scientific/Engineering :: Visualization
Project-URL: Homepage, https://github.com/shakfu/hola-graph
Project-URL: Repository, https://github.com/shakfu/hola-graph
Project-URL: Issues, https://github.com/shakfu/hola-graph/issues
Requires-Python: >=3.9
Provides-Extra: networkx
Requires-Dist: networkx>=2.6; extra == "networkx"
Provides-Extra: plot
Requires-Dist: matplotlib>=3.5; extra == "plot"
Provides-Extra: all
Requires-Dist: networkx>=2.6; extra == "all"
Requires-Dist: matplotlib>=3.5; extra == "all"
